arcade_google_news/__init__.py
arcade_google_news/constants.py
arcade_google_news/exceptions.py
arcade_google_news/google_data.py
arcade_google_news/types.py
arcade_google_news/utils.py
arcade_google_news/tools/__init__.py
arcade_google_news/tools/google_news.py
arcade_google_news-3.1.2.dist-info/METADATA
arcade_google_news-3.1.2.dist-info/WHEEL
arcade_google_news-3.1.2.dist-info/licenses/LICENSE
arcade_google_news-3.1.2.dist-info/RECORD
